sicp/__init__.py
sicp/__main__.py
sicp/auth.py
sicp/autograder.py
sicp/build.py
sicp/clone.py
sicp/pr.py
sicp/rpc.py
sicp/send.py
sicp/slack.py
sicp/slack_export.py
sicp/venv.py
sicp/common/__init__.py
sicp/common/cli_utils.py
sicp/common/course_config.py
sicp/common/db.py
sicp/common/hash_utils.py
sicp/common/html.py
sicp/common/jobs.py
sicp/common/oauth_client.py
sicp/common/permissions.py
sicp/common/secrets.py
sicp/common/shell_utils.py
sicp/common/url_for.py
sicp/common/rpc/__init__.py
sicp/common/rpc/ag_master.py
sicp/common/rpc/ag_worker.py
sicp/common/rpc/auth.py
sicp/common/rpc/auth_utils.py
sicp/common/rpc/buildserver.py
sicp/common/rpc/buildserver_hosted_worker.py
sicp/common/rpc/code.py
sicp/common/rpc/domains.py
sicp/common/rpc/hosted.py
sicp/common/rpc/howamidoing.py
sicp/common/rpc/indexer.py
sicp/common/rpc/mail.py
sicp/common/rpc/oh.py
sicp/common/rpc/paste.py
sicp/common/rpc/sandbox.py
sicp/common/rpc/search.py
sicp/common/rpc/secrets.py
sicp/common/rpc/sections.py
sicp/common/rpc/slack.py
sicp/common/rpc/utils.py
sicp-0.1.39.dist-info/METADATA
sicp-0.1.39.dist-info/WHEEL
sicp-0.1.39.dist-info/entry_points.txt
sicp-0.1.39.dist-info/top_level.txt
sicp-0.1.39.dist-info/RECORD
