Metadata-Version: 2.1
Name: sicp
Version: 0.1.39
Summary: UNKNOWN
Home-page: UNKNOWN
Author: Rahul Arya, Vanshaj Singhania
Author-email: rahularya@berkeley.edu
License: MIT
Platform: UNKNOWN
Requires-Python: >=3.6
Requires-Dist: click
Requires-Dist: watchdog
Requires-Dist: crcmod
Requires-Dist: tqdm
Requires-Dist: flask
Requires-Dist: cachetools
Requires-Dist: colorama
Requires-Dist: requests
Requires-Dist: PyGithub
Requires-Dist: npyscreen
